{
  "updatedAt": "2026-07-24T08:34:40.296Z",
  "events": [
    {
      "type": "WatchEvent",
      "repo": "TryCaspian/caspian-sdk",
      "summary": "starred",
      "at": "2026-07-21T09:51:02Z"
    },
    {
      "type": "CreateEvent",
      "repo": "Begarudev/raftkvcache",
      "summary": "created repo",
      "at": "2026-07-20T02:51:16Z"
    },
    {
      "type": "CreateEvent",
      "repo": "Begarudev/shrike",
      "summary": "created repo",
      "at": "2026-07-20T01:19:36Z"
    }
  ],
  "currently": [
    "Building a public RAG benchmark (BM25 + ColBERT + RRF)",
    "Porting the Go limit-order-book matching engine to C++",
    "Open to YC AI / dev-tool internships, Summer 2026"
  ]
}
